{
  "id": "danish-A1-01",
  "title": "Who Are You?",
  "theme": "Identity & introductions",
  "communicationGoal": "Introduce yourself, state your name, nationality, age, and job title in Danish",
  "cefrLevel": "A1",
  "vocabularyItemIds": [
    "A1-01-v-jeg-5325",
    "A1-01-v-du-5494",
    "A1-01-v-han-5047",
    "A1-01-v-hun-9359",
    "A1-01-v-at-hedde-3560",
    "A1-01-v-at-vaere-6550",
    "A1-01-v-at-komme-fra-9092",
    "A1-01-v-at-arbejde-8546",
    "A1-01-v-at-tale-9021",
    "A1-01-v-at-bo-8090",
    "A1-01-v-hej-8451",
    "A1-01-v-goddag-8450",
    "A1-01-v-farvel-8147",
    "A1-01-v-tak-6222",
    "A1-01-v-undskyld-2509",
    "A1-01-v-dansk-1871",
    "A1-01-v-engelsk-6827",
    "A1-01-v-tysk-9758",
    "A1-01-v-svensk-4677",
    "A1-01-v-norsk-5086",
    "A1-01-v-laerer-2287",
    "A1-01-v-ingenioer-7025",
    "A1-01-v-laege-6241",
    "A1-01-v-direktoer-8378",
    "A1-01-v-studerende-2844",
    "A1-01-v-navn-3032",
    "A1-01-v-aar-5206",
    "A1-01-v-en-8962",
    "A1-01-v-to-7983",
    "A1-01-v-tre-3715",
    "A1-01-v-fire-8356",
    "A1-01-v-fem-5349",
    "A1-01-v-seks-2450",
    "A1-01-v-syv-5346",
    "A1-01-v-otte-3002",
    "A1-01-v-ni-9203",
    "A1-01-v-ti-2184",
    "A1-01-v-elleve-4172",
    "A1-01-v-tolv-7716",
    "A1-01-v-tretten-2223",
    "A1-01-v-fjorten-3694",
    "A1-01-v-femten-1346",
    "A1-01-v-seksten-7128",
    "A1-01-v-sytten-7233",
    "A1-01-v-atten-7168",
    "A1-01-v-nitten-7496",
    "A1-01-v-tyve-3177"
  ],
  "grammarConceptIds": [
    "A1-01-g-present-tense-nutid-6604",
    "A1-01-g-personal-pronouns-1656",
    "A1-01-g-main-clause-word-order-5638"
  ],
  "createdAt": "2026-05-31T00:00:00Z",
  "isUserGenerated": false
}
